src/__init__.py
src/cli/__init__.py
src/cli/commands.py
src/db/__init__.py
src/db/client.py
src/db/operations.py
src/llm/__init__.py
src/llm/client.py
src/llm/embeddings.py
src/llm/segmentation.py
src/schemas/__init__.py
src/schemas/models.py
vibe_engineering-0.1.12.dist-info/METADATA
vibe_engineering-0.1.12.dist-info/WHEEL
vibe_engineering-0.1.12.dist-info/top_level.txt
vibe_engineering-0.1.12.dist-info/RECORD
