Metadata-Version: 2.4
Name: vibe-engineering
Version: 0.1.12
Summary: Add your description here
Home-page: https://github.com/vibeengineering/vibe-engineering
Author: Vibe Engineering Team
Author-email: team@vibeengineering.com
Requires-Python: >=3.10
Requires-Dist: certifi>=2024.12.14
Requires-Dist: fireworks-ai>=0.19.19
Requires-Dist: pydantic>=2.12.0
Requires-Dist: pymongo>=4.15.3
Requires-Dist: python-dotenv>=1.1.1
Requires-Dist: requests>=2.32.0
Requires-Dist: rich>=14.2.0
Requires-Dist: typer>=0.19.2
Dynamic: author
Dynamic: author-email
Dynamic: home-page
Dynamic: requires-python
